spotizerr_auth/__init__.py
spotizerr_auth/main.py
spotizerr_auth-1.1.1.dist-info/METADATA
spotizerr_auth-1.1.1.dist-info/WHEEL
spotizerr_auth-1.1.1.dist-info/entry_points.txt
spotizerr_auth-1.1.1.dist-info/top_level.txt
spotizerr_auth-1.1.1.dist-info/RECORD
