Metadata-Version: 2.4
Name: spotizerr-auth
Version: 1.1.1
Summary: A Spotizerr authentication utility for configuring Spotify credentials
Home-page: https://github.com/Xoconoch/spotizerr-auth
Author: spotizerr-dev
License: GPL-3.0-or-later
Classifier: Programming Language :: Python :: 3
Classifier: License :: OSI Approved :: GNU General Public License v3 or later (GPLv3+)
Classifier: Operating System :: OS Independent
Requires-Python: >=3.7
Requires-Dist: librespot-spotizerr==0.3.0
Requires-Dist: requests
Requires-Dist: rich
